MANIFEST.in
README.rst
requirements.txt
setup.py
taskwarrior_timecrimes/__init__.py
taskwarrior_timecrimes/cmdline.py
taskwarrior_timecrimes/undo_reader.py
taskwarrior_timecrimes.egg-info/PKG-INFO
taskwarrior_timecrimes.egg-info/SOURCES.txt
taskwarrior_timecrimes.egg-info/dependency_links.txt
taskwarrior_timecrimes.egg-info/entry_points.txt
taskwarrior_timecrimes.egg-info/requires.txt
taskwarrior_timecrimes.egg-info/top_level.txt