Metadata-Version: 1.1
Name: taskwarrior-timecrimes
Version: 0.1.2
Summary: Travel back in time so you can undo your duplicate tasks' creation.
Home-page: https://github.com/coddingtonbear/taskwarrior-timecrimes
Author: Adam Coddington
Author-email: me@adamcoddington.net
License: UNKNOWN
Platform: UNKNOWN
Classifier: License :: OSI Approved :: MIT License
Classifier: Operating System :: OS Independent
